MANIFEST.in
README
setup.py
config/__init__.py
config/__init__.pyc
config/settings.py
config/urls.py
config/utils.py
config/management/__init__.py
config/management/commands/__init__.py
config/management/commands/make_config.py
config/redsolution_setup/__init__.py
config/redsolution_setup/admin.py
config/redsolution_setup/make.py
config/redsolution_setup/models.py
config/redsolution_setup/urls.py
config/redsolution_setup/templates/config/redsolutioncms/buildout.cfg
config/redsolution_setup/templates/config/redsolutioncms/develop.cfg
config/redsolution_setup/templates/config/redsolutioncms/settings.pyt
config/redsolution_setup/templates/config/redsolutioncms/urls.pyt
config/templates/config/disable.py.conf
config/templates/config/duply_conf.conf
config/templates/config/duply_exclude.conf
config/templates/config/duply_post.conf
config/templates/config/duply_pre.conf
config/templates/config/enable.py.conf
config/templates/config/httpd.conf
config/templates/config/init.d.conf
config/templates/config/install.py.conf
config/templates/config/lighttpd.conf
config/templates/config/logrotate.conf
config/templates/config/monit.conf
config/templates/config/uninstall.py.conf
config/templatetags/__init__.py
config/templatetags/config_tags.py
redsolutioncms.django_server_config.egg-info/PKG-INFO
redsolutioncms.django_server_config.egg-info/SOURCES.txt
redsolutioncms.django_server_config.egg-info/dependency_links.txt
redsolutioncms.django_server_config.egg-info/entry_points.txt
redsolutioncms.django_server_config.egg-info/not-zip-safe
redsolutioncms.django_server_config.egg-info/requires.txt
redsolutioncms.django_server_config.egg-info/top_level.txt