Metadata-Version: 1.0
Name: redsolutioncms.django-server-config
Version: 0.1.4
Summary: Useful for deploy server installation. 
Home-page: UNKNOWN
Author: Ivan Gromov
Author-email: ivan.gromov@redsolution.ru
License: GPLv3
Keywords: django config lighttpd apache monit
Platform: UNKNOWN
Classifier: Development Status :: 3 - Alpha
Classifier: Intended Audience :: Developers
Classifier: License :: OSI Approved :: GNU General Public License (GPL)
Classifier: Framework :: Django
Classifier: Environment :: Web Environment
Classifier: Natural Language :: Russian
Classifier: Natural Language :: English
Classifier: Operating System :: OS Independent
Classifier: Programming Language :: Python
Classifier: Topic :: Internet :: WWW/HTTP :: Site Management
